mattermost/__init__.py
mattermost/stdin2channel.py
mattermost/version.py
mattermost/ws.py
mattermost_notify/__init__.py
mattermost_notify/api.py
mattermost_notify/cli.py
mattermost_notify/client.py
mattermost_notify/config.py
mattermost_tools-0.0.4.dist-info/licenses/LICENSE
mattermost_tools-0.0.4.dist-info/METADATA
mattermost_tools-0.0.4.dist-info/WHEEL
mattermost_tools-0.0.4.dist-info/entry_points.txt
mattermost_tools-0.0.4.dist-info/top_level.txt
mattermost_tools-0.0.4.dist-info/RECORD
