Metadata-Version: 2.4
Name: mattermost-tools
Version: 0.0.4
Summary: A tool to send notifications to Mattermost and manage Mattermost channels and users.
Home-page: https://github.com/neil-karania/mattermost-tools
Author: Neil Karania
Author-email: neil.karania19@gmail.com
License: MIT
License-File: LICENSE
Requires-Dist: requests
Requires-Dist: argparse
Requires-Dist: websockets
Requires-Dist: bs4
Dynamic: author
Dynamic: author-email
Dynamic: description
Dynamic: description-content-type
Dynamic: home-page
Dynamic: license
Dynamic: license-file
Dynamic: requires-dist
Dynamic: summary
